OhlcvAnalyser/MultiOhlcvAnalyser.py
OhlcvAnalyser/SingleOhlcvAnalyser.py
OhlcvAnalyser/__init__.py
OhlcvAnalyser/analyser/CoefficientAnalyser.py
OhlcvAnalyser/analyser/PriceAnalyser.py
OhlcvAnalyser/analyser/ProfitAnalyser.py
OhlcvAnalyser/analyser/VarianceAnalyser.py
OhlcvAnalyser/analyser/__init__.py
OhlcvAnalyser/plotter/__init__.py
OhlcvAnalyser/plotter/plotter.py
OhlcvAnalyser/utils/__init__.py
OhlcvAnalyser/utils/coefficient.py
OhlcvAnalyser/utils/date.py
OhlcvAnalyser/utils/profit.py
blueprint/MultiOhlcvAnalyser.py
blueprint/SingleOhlcvAnalyser.py
blueprint/__init__.py
OhlcvAnalyser-1.0.2.dist-info/METADATA
OhlcvAnalyser-1.0.2.dist-info/WHEEL
OhlcvAnalyser-1.0.2.dist-info/top_level.txt
OhlcvAnalyser-1.0.2.dist-info/RECORD
