Metadata-Version: 2.1
Name: OhlcvAnalyser
Version: 1.0.2
Summary: OhlcvAnalyser
Home-page: https://github.com/jackmappotion/OhlcvAnalyser
Author: jackmappotion
Author-email: jackmappotion@gmail.com
